msqla/__init__.py
msqla/py.typed
msqla/dialect/base/dialect.py
msqla-0.1.0.dist-info/METADATA
msqla-0.1.0.dist-info/WHEEL
msqla-0.1.0.dist-info/RECORD
