Metadata-Version: 2.4
Name: msqla
Version: 0.1.0
Summary: Next-level sharded queries with sqlalchemy.
Author-email: julianvanmeggelen <julianvanmeggelen@gmail.com>
Requires-Python: >=3.10
Requires-Dist: sqlalchemy>=2.0.39
